LICENSE
README.md
setup.py
dejax/__init__.py
dejax/base.py
dejax/circular_buffer.py
dejax/clustered.py
dejax/uniform.py
dejax/utils.py
dejax.egg-info/PKG-INFO
dejax.egg-info/SOURCES.txt
dejax.egg-info/dependency_links.txt
dejax.egg-info/requires.txt
dejax.egg-info/top_level.txt